maps/__init__.py
maps/_version.py
maps/apis/apis.py
maps/apis/mapbox.py
maps/commands.py
maps/exceptions.py
maps/here.py
maps/mapbox.py
maps/ors.py
maps/osm.py
maps/tomtom.py
maps/utils.py
maps_cli-0.0.4.dist-info/entry_points.txt
maps_cli-0.0.4.dist-info/LICENSE
maps_cli-0.0.4.dist-info/WHEEL
maps_cli-0.0.4.dist-info/METADATA
maps_cli-0.0.4.dist-info/RECORD
