Metadata-Version: 2.1
Name: maps-cli
Version: 0.0.4
Summary: A CLI for maps services.
Home-page: https://github.com/sackh/maps-cli
License: MIT
Keywords: cli,maps
Author: Sachin Kharude
Author-email: sachinkharude10@gmail.com
Requires-Python: >=3.7.1,<4.0
Classifier: Development Status :: 4 - Beta
Classifier: Intended Audience :: Developers
Classifier: License :: OSI Approved :: MIT License
Classifier: Programming Language :: Python :: 3
Classifier: Programming Language :: Python :: 3 :: Only
Classifier: Programming Language :: Python :: 3.7
Classifier: Programming Language :: Python :: 3.8
Classifier: Programming Language :: Python :: 3.9
Classifier: Topic :: Software Development :: Libraries
Requires-Dist: click (>=7.1.2,<8.0.0)
Requires-Dist: geojson (>=2.5.0,<3.0.0)
Requires-Dist: geojsonio (>=0.0.3,<0.0.4)
Requires-Dist: geopy (>=2.1.0,<3.0.0)
Requires-Dist: here-location-services (>=0.2.0,<0.3.0)
Requires-Dist: openrouteservice (>=2.3.3,<3.0.0)
Requires-Dist: overpy (>=0.4,<0.5)
Requires-Dist: requests (>=2.25.1,<3.0.0)
Requires-Dist: simplejson (>=3.17.2,<4.0.0)
Project-URL: Bug Tracker, https://github.com/sackh/maps-cli/issues
Project-URL: Repository, https://github.com/sackh/maps-cli
